WebSpeechRecognition/__init__.py
WebSpeechRecognition/main.py
WebSpeechRecognition/web.html
WebSpeechRecognition-0.1.4.dist-info/LICENSE
WebSpeechRecognition-0.1.4.dist-info/METADATA
WebSpeechRecognition-0.1.4.dist-info/WHEEL
WebSpeechRecognition-0.1.4.dist-info/top_level.txt
WebSpeechRecognition-0.1.4.dist-info/RECORD
