Metadata-Version: 2.1
Name: WebSpeechRecognition
Version: 0.1.4
Summary: A Python library for speech-to-text integration using Selenium WebDriver.
Home-page: UNKNOWN
Author: Arnav Singh
Author-email: authentic.arnav@gmail.com
License: UNKNOWN
Keywords: python,speech,recognition,speech recognition,stt,selenium,speech-to-text,selenium,voice recognition,voice interaction,multilingual,multilingual support,chromedriver
Platform: UNKNOWN
Requires-Python: >=3.7
Requires-Dist: selenium>=4.0.0
